loggermodule_X/__init__.py
loggermodule_X/loggermodule_X.py
loggermodule_X/test/loggermodule_XS.py
loggermodule_X/test/test_log.py
loggermodule_X/test/test02/test_log_02.py
loggermodule_X-2.1.dist-info/METADATA
loggermodule_X-2.1.dist-info/WHEEL
loggermodule_X-2.1.dist-info/top_level.txt
loggermodule_X-2.1.dist-info/RECORD
