Metadata-Version: 2.1
Name: loggermodule-X
Version: 2.1
Summary: Just logging :)
Author-email: "KHUNANON.C" <khunanon@infoquest.co.th>
Project-URL: Homepage, https://dataxet.infoquest.co.th/
Project-URL: Bug Tracker, https://dataxet.infoquest.co.th/
Classifier: Programming Language :: Python :: 3.8
Classifier: Programming Language :: Python :: 3.11
Classifier: License :: OSI Approved :: MIT License
Classifier: Operating System :: OS Independent
Requires-Python: >=3.8
